mpldatacursor/__init__.py
mpldatacursor/convenience.py
mpldatacursor/datacursor.py
mpldatacursor/pick_info.py
mpldatacursor-0.7.1.dist-info/LICENSE
mpldatacursor-0.7.1.dist-info/METADATA
mpldatacursor-0.7.1.dist-info/WHEEL
mpldatacursor-0.7.1.dist-info/top_level.txt
mpldatacursor-0.7.1.dist-info/RECORD
